[
  {
    "idU": 0,
    "name": {
      "first": "Angelia",
      "last": "Barrera"
    },
    "pseudo": "Angelia8",
    "passWord": "AngeliaBARRERA447"
  },
  {
    "idU": 1,
    "name": {
      "first": "Therese",
      "last": "Nash"
    },
    "pseudo": "Therese2",
    "passWord": "ThereseNASH183"
  },
  {
    "idU": 2,
    "name": {
      "first": "Baird",
      "last": "Battle"
    },
    "pseudo": "Baird8",
    "passWord": "BairdBATTLE83"
  },
  {
    "idU": 3,
    "name": {
      "first": "Enid",
      "last": "Mcneil"
    },
    "pseudo": "Enid8",
    "passWord": "EnidMCNEIL584"
  },
  {
    "idU": 4,
    "name": {
      "first": "Iris",
      "last": "Cortez"
    },
    "pseudo": "Iris7",
    "passWord": "IrisCORTEZ300"
  },
  {
    "idU": 5,
    "name": {
      "first": "Nguyen",
      "last": "Christian"
    },
    "pseudo": "Nguyen4",
    "passWord": "NguyenCHRISTIAN626"
  },
  {
    "idU": 6,
    "name": {
      "first": "Copeland",
      "last": "Romero"
    },
    "pseudo": "Copeland8",
    "passWord": "CopelandROMERO478"
  },
  {
    "idU": 7,
    "name": {
      "first": "Lorna",
      "last": "Mcintosh"
    },
    "pseudo": "Lorna10",
    "passWord": "LornaMCINTOSH438"
  },
  {
    "idU": 8,
    "name": {
      "first": "Ella",
      "last": "Chaney"
    },
    "pseudo": "Ella8",
    "passWord": "EllaCHANEY678"
  },
  {
    "idU": 9,
    "name": {
      "first": "Patricia",
      "last": "Monroe"
    },
    "pseudo": "Patricia8",
    "passWord": "PatriciaMONROE774"
  },
  {
    "idU": 10,
    "name": {
      "first": "Joseph",
      "last": "Wooten"
    },
    "pseudo": "Joseph5",
    "passWord": "JosephWOOTEN506"
  },
  {
    "idU": 11,
    "name": {
      "first": "Kris",
      "last": "Boyer"
    },
    "pseudo": "Kris3",
    "passWord": "KrisBOYER68"
  },
  {
    "idU": 12,
    "name": {
      "first": "Quinn",
      "last": "Delgado"
    },
    "pseudo": "Quinn8",
    "passWord": "QuinnDELGADO683"
  },
  {
    "idU": 13,
    "name": {
      "first": "Boyle",
      "last": "Thornton"
    },
    "pseudo": "Boyle5",
    "passWord": "BoyleTHORNTON353"
  },
  {
    "idU": 14,
    "name": {
      "first": "Mills",
      "last": "Joseph"
    },
    "pseudo": "Mills5",
    "passWord": "MillsJOSEPH632"
  },
  {
    "idU": 15,
    "name": {
      "first": "Hale",
      "last": "Shepherd"
    },
    "pseudo": "Hale5",
    "passWord": "HaleSHEPHERD536"
  },
  {
    "idU": 16,
    "name": {
      "first": "Hardy",
      "last": "Jacobs"
    },
    "pseudo": "Hardy2",
    "passWord": "HardyJACOBS119"
  },
  {
    "idU": 17,
    "name": {
      "first": "Madeline",
      "last": "Oliver"
    },
    "pseudo": "Madeline6",
    "passWord": "MadelineOLIVER865"
  },
  {
    "idU": 18,
    "name": {
      "first": "Earlene",
      "last": "Knowles"
    },
    "pseudo": "Earlene1",
    "passWord": "EarleneKNOWLES25"
  },
  {
    "idU": 19,
    "name": {
      "first": "Francine",
      "last": "Nielsen"
    },
    "pseudo": "Francine9",
    "passWord": "FrancineNIELSEN579"
  },
  {
    "idU": 20,
    "name": {
      "first": "Ginger",
      "last": "Wade"
    },
    "pseudo": "Ginger2",
    "passWord": "GingerWADE62"
  },
  {
    "idU": 21,
    "name": {
      "first": "Kathryn",
      "last": "Andrews"
    },
    "pseudo": "Kathryn9",
    "passWord": "KathrynANDREWS383"
  },
  {
    "idU": 22,
    "name": {
      "first": "Jamie",
      "last": "Cook"
    },
    "pseudo": "Jamie9",
    "passWord": "JamieCOOK466"
  },
  {
    "idU": 23,
    "name": {
      "first": "Helga",
      "last": "Berg"
    },
    "pseudo": "Helga7",
    "passWord": "HelgaBERG646"
  },
  {
    "idU": 24,
    "name": {
      "first": "Riddle",
      "last": "Beck"
    },
    "pseudo": "Riddle7",
    "passWord": "RiddleBECK178"
  },
  {
    "idU": 25,
    "name": {
      "first": "Davis",
      "last": "Daniels"
    },
    "pseudo": "Davis6",
    "passWord": "DavisDANIELS841"
  },
  {
    "idU": 26,
    "name": {
      "first": "Margret",
      "last": "Velez"
    },
    "pseudo": "Margret1",
    "passWord": "MargretVELEZ682"
  },
  {
    "idU": 27,
    "name": {
      "first": "Norman",
      "last": "Chapman"
    },
    "pseudo": "Norman5",
    "passWord": "NormanCHAPMAN233"
  },
  {
    "idU": 28,
    "name": {
      "first": "Michelle",
      "last": "Todd"
    },
    "pseudo": "Michelle8",
    "passWord": "MichelleTODD497"
  },
  {
    "idU": 29,
    "name": {
      "first": "Fran",
      "last": "Gallegos"
    },
    "pseudo": "Fran5",
    "passWord": "FranGALLEGOS341"
  },
  {
    "idU": 30,
    "name": {
      "first": "Chandra",
      "last": "Maynard"
    },
    "pseudo": "Chandra5",
    "passWord": "ChandraMAYNARD42"
  },
  {
    "idU": 31,
    "name": {
      "first": "Peters",
      "last": "Bright"
    },
    "pseudo": "Peters6",
    "passWord": "PetersBRIGHT255"
  },
  {
    "idU": 32,
    "name": {
      "first": "Carissa",
      "last": "Vinson"
    },
    "pseudo": "Carissa3",
    "passWord": "CarissaVINSON293"
  },
  {
    "idU": 33,
    "name": {
      "first": "Bridgette",
      "last": "Carey"
    },
    "pseudo": "Bridgette8",
    "passWord": "BridgetteCAREY702"
  },
  {
    "idU": 34,
    "name": {
      "first": "Bryant",
      "last": "Bradley"
    },
    "pseudo": "Bryant7",
    "passWord": "BryantBRADLEY843"
  },
  {
    "idU": 35,
    "name": {
      "first": "Audra",
      "last": "Mclaughlin"
    },
    "pseudo": "Audra8",
    "passWord": "AudraMCLAUGHLIN388"
  },
  {
    "idU": 36,
    "name": {
      "first": "Cross",
      "last": "Shields"
    },
    "pseudo": "Cross7",
    "passWord": "CrossSHIELDS348"
  },
  {
    "idU": 37,
    "name": {
      "first": "Bonnie",
      "last": "Mercado"
    },
    "pseudo": "Bonnie1",
    "passWord": "BonnieMERCADO265"
  },
  {
    "idU": 38,
    "name": {
      "first": "Duran",
      "last": "Hunter"
    },
    "pseudo": "Duran10",
    "passWord": "DuranHUNTER51"
  },
  {
    "idU": 39,
    "name": {
      "first": "Young",
      "last": "Oneal"
    },
    "pseudo": "Young7",
    "passWord": "YoungONEAL642"
  },
  {
    "idU": 40,
    "name": {
      "first": "Cassie",
      "last": "Gibbs"
    },
    "pseudo": "Cassie6",
    "passWord": "CassieGIBBS379"
  },
  {
    "idU": 41,
    "name": {
      "first": "Sawyer",
      "last": "Boyd"
    },
    "pseudo": "Sawyer2",
    "passWord": "SawyerBOYD233"
  },
  {
    "idU": 42,
    "name": {
      "first": "Nora",
      "last": "Vargas"
    },
    "pseudo": "Nora9",
    "passWord": "NoraVARGAS644"
  },
  {
    "idU": 43,
    "name": {
      "first": "Janine",
      "last": "Conrad"
    },
    "pseudo": "Janine9",
    "passWord": "JanineCONRAD406"
  },
  {
    "idU": 44,
    "name": {
      "first": "Williamson",
      "last": "Travis"
    },
    "pseudo": "Williamson9",
    "passWord": "WilliamsonTRAVIS92"
  },
  {
    "idU": 45,
    "name": {
      "first": "Bolton",
      "last": "Atkinson"
    },
    "pseudo": "Bolton3",
    "passWord": "BoltonATKINSON533"
  },
  {
    "idU": 46,
    "name": {
      "first": "Farley",
      "last": "Rosales"
    },
    "pseudo": "Farley8",
    "passWord": "FarleyROSALES496"
  },
  {
    "idU": 47,
    "name": {
      "first": "Madelyn",
      "last": "Wright"
    },
    "pseudo": "Madelyn2",
    "passWord": "MadelynWRIGHT571"
  },
  {
    "idU": 48,
    "name": {
      "first": "Rios",
      "last": "Hopkins"
    },
    "pseudo": "Rios2",
    "passWord": "RiosHOPKINS358"
  },
  {
    "idU": 49,
    "name": {
      "first": "Sally",
      "last": "Woodard"
    },
    "pseudo": "Sally9",
    "passWord": "SallyWOODARD448"
  },
  {
    "idU": 50,
    "name": {
      "first": "Latisha",
      "last": "Burgess"
    },
    "pseudo": "Latisha6",
    "passWord": "LatishaBURGESS15"
  },
  {
    "idU": 51,
    "name": {
      "first": "Mccarty",
      "last": "Kemp"
    },
    "pseudo": "Mccarty7",
    "passWord": "MccartyKEMP310"
  },
  {
    "idU": 52,
    "name": {
      "first": "Camacho",
      "last": "Hammond"
    },
    "pseudo": "Camacho10",
    "passWord": "CamachoHAMMOND283"
  },
  {
    "idU": 53,
    "name": {
      "first": "Travis",
      "last": "Santana"
    },
    "pseudo": "Travis3",
    "passWord": "TravisSANTANA331"
  },
  {
    "idU": 54,
    "name": {
      "first": "Mosley",
      "last": "York"
    },
    "pseudo": "Mosley8",
    "passWord": "MosleyYORK540"
  },
  {
    "idU": 55,
    "name": {
      "first": "Irwin",
      "last": "Fleming"
    },
    "pseudo": "Irwin10",
    "passWord": "IrwinFLEMING581"
  },
  {
    "idU": 56,
    "name": {
      "first": "Joyce",
      "last": "Curry"
    },
    "pseudo": "Joyce6",
    "passWord": "JoyceCURRY105"
  },
  {
    "idU": 57,
    "name": {
      "first": "Morris",
      "last": "Beard"
    },
    "pseudo": "Morris9",
    "passWord": "MorrisBEARD790"
  },
  {
    "idU": 58,
    "name": {
      "first": "Lesa",
      "last": "Malone"
    },
    "pseudo": "Lesa10",
    "passWord": "LesaMALONE383"
  },
  {
    "idU": 59,
    "name": {
      "first": "Roberson",
      "last": "Dejesus"
    },
    "pseudo": "Roberson6",
    "passWord": "RobersonDEJESUS81"
  },
  {
    "idU": 60,
    "name": {
      "first": "Debora",
      "last": "Middleton"
    },
    "pseudo": "Debora10",
    "passWord": "DeboraMIDDLETON230"
  },
  {
    "idU": 61,
    "name": {
      "first": "Mcgowan",
      "last": "Bruce"
    },
    "pseudo": "Mcgowan8",
    "passWord": "McgowanBRUCE703"
  },
  {
    "idU": 62,
    "name": {
      "first": "Rosemary",
      "last": "Mcbride"
    },
    "pseudo": "Rosemary1",
    "passWord": "RosemaryMCBRIDE155"
  },
  {
    "idU": 63,
    "name": {
      "first": "Esperanza",
      "last": "Harrell"
    },
    "pseudo": "Esperanza10",
    "passWord": "EsperanzaHARRELL71"
  },
  {
    "idU": 64,
    "name": {
      "first": "Johnnie",
      "last": "Russo"
    },
    "pseudo": "Johnnie9",
    "passWord": "JohnnieRUSSO751"
  },
  {
    "idU": 65,
    "name": {
      "first": "Shepard",
      "last": "Key"
    },
    "pseudo": "Shepard2",
    "passWord": "ShepardKEY522"
  },
  {
    "idU": 66,
    "name": {
      "first": "Jean",
      "last": "Rocha"
    },
    "pseudo": "Jean3",
    "passWord": "JeanROCHA254"
  },
  {
    "idU": 67,
    "name": {
      "first": "Fulton",
      "last": "Fisher"
    },
    "pseudo": "Fulton8",
    "passWord": "FultonFISHER372"
  },
  {
    "idU": 68,
    "name": {
      "first": "Connie",
      "last": "Sweet"
    },
    "pseudo": "Connie7",
    "passWord": "ConnieSWEET302"
  },
  {
    "idU": 69,
    "name": {
      "first": "Mcdaniel",
      "last": "Gates"
    },
    "pseudo": "Mcdaniel4",
    "passWord": "McdanielGATES24"
  },
  {
    "idU": 70,
    "name": {
      "first": "Lancaster",
      "last": "Wilcox"
    },
    "pseudo": "Lancaster2",
    "passWord": "LancasterWILCOX75"
  },
  {
    "idU": 71,
    "name": {
      "first": "Roslyn",
      "last": "Olsen"
    },
    "pseudo": "Roslyn4",
    "passWord": "RoslynOLSEN678"
  },
  {
    "idU": 72,
    "name": {
      "first": "Mai",
      "last": "Calhoun"
    },
    "pseudo": "Mai5",
    "passWord": "MaiCALHOUN540"
  },
  {
    "idU": 73,
    "name": {
      "first": "Jana",
      "last": "Page"
    },
    "pseudo": "Jana8",
    "passWord": "JanaPAGE241"
  },
  {
    "idU": 74,
    "name": {
      "first": "Lillie",
      "last": "Walker"
    },
    "pseudo": "Lillie5",
    "passWord": "LillieWALKER559"
  },
  {
    "idU": 75,
    "name": {
      "first": "Maddox",
      "last": "Wolfe"
    },
    "pseudo": "Maddox8",
    "passWord": "MaddoxWOLFE681"
  },
  {
    "idU": 76,
    "name": {
      "first": "Lucia",
      "last": "Lott"
    },
    "pseudo": "Lucia4",
    "passWord": "LuciaLOTT325"
  },
  {
    "idU": 77,
    "name": {
      "first": "Lowery",
      "last": "Hubbard"
    },
    "pseudo": "Lowery6",
    "passWord": "LoweryHUBBARD191"
  },
  {
    "idU": 78,
    "name": {
      "first": "Rich",
      "last": "Parker"
    },
    "pseudo": "Rich4",
    "passWord": "RichPARKER226"
  },
  {
    "idU": 79,
    "name": {
      "first": "Shaffer",
      "last": "Williams"
    },
    "pseudo": "Shaffer7",
    "passWord": "ShafferWILLIAMS437"
  },
  {
    "idU": 80,
    "name": {
      "first": "Bessie",
      "last": "Cole"
    },
    "pseudo": "Bessie5",
    "passWord": "BessieCOLE872"
  },
  {
    "idU": 81,
    "name": {
      "first": "Lilia",
      "last": "Spencer"
    },
    "pseudo": "Lilia10",
    "passWord": "LiliaSPENCER373"
  },
  {
    "idU": 82,
    "name": {
      "first": "Gonzales",
      "last": "Turner"
    },
    "pseudo": "Gonzales8",
    "passWord": "GonzalesTURNER612"
  },
  {
    "idU": 83,
    "name": {
      "first": "Strickland",
      "last": "Booth"
    },
    "pseudo": "Strickland9",
    "passWord": "StricklandBOOTH383"
  },
  {
    "idU": 84,
    "name": {
      "first": "Clements",
      "last": "Herman"
    },
    "pseudo": "Clements10",
    "passWord": "ClementsHERMAN60"
  },
  {
    "idU": 85,
    "name": {
      "first": "Marquita",
      "last": "Cline"
    },
    "pseudo": "Marquita5",
    "passWord": "MarquitaCLINE738"
  },
  {
    "idU": 86,
    "name": {
      "first": "Myrna",
      "last": "Sloan"
    },
    "pseudo": "Myrna6",
    "passWord": "MyrnaSLOAN187"
  },
  {
    "idU": 87,
    "name": {
      "first": "Rosanna",
      "last": "Melendez"
    },
    "pseudo": "Rosanna5",
    "passWord": "RosannaMELENDEZ350"
  },
  {
    "idU": 88,
    "name": {
      "first": "Waller",
      "last": "Chandler"
    },
    "pseudo": "Waller2",
    "passWord": "WallerCHANDLER614"
  },
  {
    "idU": 89,
    "name": {
      "first": "Frankie",
      "last": "Farley"
    },
    "pseudo": "Frankie2",
    "passWord": "FrankieFARLEY822"
  },
  {
    "idU": 90,
    "name": {
      "first": "Maxine",
      "last": "Medina"
    },
    "pseudo": "Maxine2",
    "passWord": "MaxineMEDINA119"
  },
  {
    "idU": 91,
    "name": {
      "first": "Hazel",
      "last": "Gilliam"
    },
    "pseudo": "Hazel10",
    "passWord": "HazelGILLIAM66"
  },
  {
    "idU": 92,
    "name": {
      "first": "Cunningham",
      "last": "Dickerson"
    },
    "pseudo": "Cunningham9",
    "passWord": "CunninghamDICKERSON708"
  },
  {
    "idU": 93,
    "name": {
      "first": "Farmer",
      "last": "Vaughn"
    },
    "pseudo": "Farmer5",
    "passWord": "FarmerVAUGHN545"
  },
  {
    "idU": 94,
    "name": {
      "first": "Green",
      "last": "Francis"
    },
    "pseudo": "Green5",
    "passWord": "GreenFRANCIS310"
  },
  {
    "idU": 95,
    "name": {
      "first": "Mcintyre",
      "last": "Richard"
    },
    "pseudo": "Mcintyre6",
    "passWord": "McintyreRICHARD501"
  },
  {
    "idU": 96,
    "name": {
      "first": "Terrell",
      "last": "Barnett"
    },
    "pseudo": "Terrell7",
    "passWord": "TerrellBARNETT568"
  },
  {
    "idU": 97,
    "name": {
      "first": "Swanson",
      "last": "Serrano"
    },
    "pseudo": "Swanson9",
    "passWord": "SwansonSERRANO868"
  },
  {
    "idU": 98,
    "name": {
      "first": "Alison",
      "last": "Hampton"
    },
    "pseudo": "Alison5",
    "passWord": "AlisonHAMPTON823"
  },
  {
    "idU": 99,
    "name": {
      "first": "Viola",
      "last": "Greer"
    },
    "pseudo": "Viola9",
    "passWord": "ViolaGREER840"
  },
  {
    "idU": 100,
    "name": {
      "first": "Stark",
      "last": "Sheppard"
    },
    "pseudo": "Stark2",
    "passWord": "StarkSHEPPARD62"
  },
  {
    "idU": 101,
    "name": {
      "first": "Erica",
      "last": "Mclean"
    },
    "pseudo": "Erica3",
    "passWord": "EricaMCLEAN671"
  },
  {
    "idU": 102,
    "name": {
      "first": "Shelia",
      "last": "Hoover"
    },
    "pseudo": "Shelia10",
    "passWord": "SheliaHOOVER74"
  },
  {
    "idU": 103,
    "name": {
      "first": "Owens",
      "last": "Galloway"
    },
    "pseudo": "Owens3",
    "passWord": "OwensGALLOWAY739"
  },
  {
    "idU": 104,
    "name": {
      "first": "Lydia",
      "last": "Cantrell"
    },
    "pseudo": "Lydia1",
    "passWord": "LydiaCANTRELL292"
  },
  {
    "idU": 105,
    "name": {
      "first": "Mclaughlin",
      "last": "Cruz"
    },
    "pseudo": "Mclaughlin1",
    "passWord": "MclaughlinCRUZ850"
  },
  {
    "idU": 106,
    "name": {
      "first": "Shana",
      "last": "Watkins"
    },
    "pseudo": "Shana4",
    "passWord": "ShanaWATKINS448"
  },
  {
    "idU": 107,
    "name": {
      "first": "Brittney",
      "last": "Gaines"
    },
    "pseudo": "Brittney10",
    "passWord": "BrittneyGAINES32"
  },
  {
    "idU": 108,
    "name": {
      "first": "Nichole",
      "last": "Conway"
    },
    "pseudo": "Nichole4",
    "passWord": "NicholeCONWAY585"
  },
  {
    "idU": 109,
    "name": {
      "first": "Cobb",
      "last": "Sweeney"
    },
    "pseudo": "Cobb4",
    "passWord": "CobbSWEENEY633"
  },
  {
    "idU": 110,
    "name": {
      "first": "Doreen",
      "last": "Ochoa"
    },
    "pseudo": "Doreen2",
    "passWord": "DoreenOCHOA48"
  },
  {
    "idU": 111,
    "name": {
      "first": "Rene",
      "last": "Briggs"
    },
    "pseudo": "Rene7",
    "passWord": "ReneBRIGGS134"
  },
  {
    "idU": 112,
    "name": {
      "first": "Malone",
      "last": "Doyle"
    },
    "pseudo": "Malone10",
    "passWord": "MaloneDOYLE384"
  },
  {
    "idU": 113,
    "name": {
      "first": "Aida",
      "last": "Byrd"
    },
    "pseudo": "Aida4",
    "passWord": "AidaBYRD257"
  },
  {
    "idU": 114,
    "name": {
      "first": "Tamika",
      "last": "Alvarez"
    },
    "pseudo": "Tamika5",
    "passWord": "TamikaALVAREZ589"
  },
  {
    "idU": 115,
    "name": {
      "first": "Frances",
      "last": "Whitney"
    },
    "pseudo": "Frances7",
    "passWord": "FrancesWHITNEY374"
  },
  {
    "idU": 116,
    "name": {
      "first": "Laverne",
      "last": "Hyde"
    },
    "pseudo": "Laverne3",
    "passWord": "LaverneHYDE91"
  },
  {
    "idU": 117,
    "name": {
      "first": "Catalina",
      "last": "Bush"
    },
    "pseudo": "Catalina4",
    "passWord": "CatalinaBUSH549"
  },
  {
    "idU": 118,
    "name": {
      "first": "Gibson",
      "last": "Stark"
    },
    "pseudo": "Gibson5",
    "passWord": "GibsonSTARK382"
  },
  {
    "idU": 119,
    "name": {
      "first": "Estela",
      "last": "Johnson"
    },
    "pseudo": "Estela2",
    "passWord": "EstelaJOHNSON138"
  },
  {
    "idU": 120,
    "name": {
      "first": "Gena",
      "last": "Burton"
    },
    "pseudo": "Gena5",
    "passWord": "GenaBURTON86"
  },
  {
    "idU": 121,
    "name": {
      "first": "Ortiz",
      "last": "Peterson"
    },
    "pseudo": "Ortiz1",
    "passWord": "OrtizPETERSON489"
  },
  {
    "idU": 122,
    "name": {
      "first": "Soto",
      "last": "Roberts"
    },
    "pseudo": "Soto10",
    "passWord": "SotoROBERTS292"
  },
  {
    "idU": 123,
    "name": {
      "first": "Mcintosh",
      "last": "Bradford"
    },
    "pseudo": "Mcintosh8",
    "passWord": "McintoshBRADFORD645"
  },
  {
    "idU": 124,
    "name": {
      "first": "Nunez",
      "last": "Cote"
    },
    "pseudo": "Nunez3",
    "passWord": "NunezCOTE272"
  },
  {
    "idU": 125,
    "name": {
      "first": "Gayle",
      "last": "Morse"
    },
    "pseudo": "Gayle8",
    "passWord": "GayleMORSE573"
  },
  {
    "idU": 126,
    "name": {
      "first": "Brandi",
      "last": "Silva"
    },
    "pseudo": "Brandi4",
    "passWord": "BrandiSILVA36"
  },
  {
    "idU": 127,
    "name": {
      "first": "Liz",
      "last": "Cannon"
    },
    "pseudo": "Liz4",
    "passWord": "LizCANNON423"
  },
  {
    "idU": 128,
    "name": {
      "first": "Eugenia",
      "last": "Franks"
    },
    "pseudo": "Eugenia2",
    "passWord": "EugeniaFRANKS258"
  },
  {
    "idU": 129,
    "name": {
      "first": "Anne",
      "last": "Noble"
    },
    "pseudo": "Anne1",
    "passWord": "AnneNOBLE95"
  },
  {
    "idU": 130,
    "name": {
      "first": "Moore",
      "last": "Hanson"
    },
    "pseudo": "Moore9",
    "passWord": "MooreHANSON636"
  },
  {
    "idU": 131,
    "name": {
      "first": "Patrick",
      "last": "Morrow"
    },
    "pseudo": "Patrick6",
    "passWord": "PatrickMORROW798"
  },
  {
    "idU": 132,
    "name": {
      "first": "Nola",
      "last": "Cooke"
    },
    "pseudo": "Nola9",
    "passWord": "NolaCOOKE772"
  },
  {
    "idU": 133,
    "name": {
      "first": "Humphrey",
      "last": "Zamora"
    },
    "pseudo": "Humphrey8",
    "passWord": "HumphreyZAMORA18"
  },
  {
    "idU": 134,
    "name": {
      "first": "Corrine",
      "last": "Stanton"
    },
    "pseudo": "Corrine2",
    "passWord": "CorrineSTANTON407"
  },
  {
    "idU": 135,
    "name": {
      "first": "Pearson",
      "last": "Peck"
    },
    "pseudo": "Pearson6",
    "passWord": "PearsonPECK258"
  },
  {
    "idU": 136,
    "name": {
      "first": "Etta",
      "last": "Buckley"
    },
    "pseudo": "Etta3",
    "passWord": "EttaBUCKLEY18"
  },
  {
    "idU": 137,
    "name": {
      "first": "Mcgee",
      "last": "Bonner"
    },
    "pseudo": "Mcgee3",
    "passWord": "McgeeBONNER601"
  },
  {
    "idU": 138,
    "name": {
      "first": "Sanford",
      "last": "Obrien"
    },
    "pseudo": "Sanford5",
    "passWord": "SanfordOBRIEN765"
  },
  {
    "idU": 139,
    "name": {
      "first": "Phyllis",
      "last": "Sanchez"
    },
    "pseudo": "Phyllis2",
    "passWord": "PhyllisSANCHEZ496"
  },
  {
    "idU": 140,
    "name": {
      "first": "Lenora",
      "last": "Williamson"
    },
    "pseudo": "Lenora1",
    "passWord": "LenoraWILLIAMSON326"
  },
  {
    "idU": 141,
    "name": {
      "first": "Elva",
      "last": "Hill"
    },
    "pseudo": "Elva10",
    "passWord": "ElvaHILL258"
  },
  {
    "idU": 142,
    "name": {
      "first": "Susana",
      "last": "Witt"
    },
    "pseudo": "Susana4",
    "passWord": "SusanaWITT361"
  },
  {
    "idU": 143,
    "name": {
      "first": "Candy",
      "last": "Griffith"
    },
    "pseudo": "Candy5",
    "passWord": "CandyGRIFFITH202"
  },
  {
    "idU": 144,
    "name": {
      "first": "Walters",
      "last": "Mullins"
    },
    "pseudo": "Walters10",
    "passWord": "WaltersMULLINS888"
  },
  {
    "idU": 145,
    "name": {
      "first": "Ryan",
      "last": "Mueller"
    },
    "pseudo": "Ryan8",
    "passWord": "RyanMUELLER864"
  },
  {
    "idU": 146,
    "name": {
      "first": "Bird",
      "last": "Atkins"
    },
    "pseudo": "Bird5",
    "passWord": "BirdATKINS851"
  },
  {
    "idU": 147,
    "name": {
      "first": "Stout",
      "last": "Rivera"
    },
    "pseudo": "Stout1",
    "passWord": "StoutRIVERA515"
  },
  {
    "idU": 148,
    "name": {
      "first": "Randolph",
      "last": "Price"
    },
    "pseudo": "Randolph4",
    "passWord": "RandolphPRICE546"
  },
  {
    "idU": 149,
    "name": {
      "first": "Alyce",
      "last": "Horton"
    },
    "pseudo": "Alyce4",
    "passWord": "AlyceHORTON825"
  },
  {
    "idU": 150,
    "name": {
      "first": "Sheryl",
      "last": "Terry"
    },
    "pseudo": "Sheryl7",
    "passWord": "SherylTERRY582"
  },
  {
    "idU": 151,
    "name": {
      "first": "Sloan",
      "last": "Lowery"
    },
    "pseudo": "Sloan5",
    "passWord": "SloanLOWERY436"
  },
  {
    "idU": 152,
    "name": {
      "first": "Caitlin",
      "last": "Patton"
    },
    "pseudo": "Caitlin9",
    "passWord": "CaitlinPATTON696"
  },
  {
    "idU": 153,
    "name": {
      "first": "Abby",
      "last": "Suarez"
    },
    "pseudo": "Abby3",
    "passWord": "AbbySUAREZ82"
  },
  {
    "idU": 154,
    "name": {
      "first": "Inez",
      "last": "Caldwell"
    },
    "pseudo": "Inez2",
    "passWord": "InezCALDWELL107"
  },
  {
    "idU": 155,
    "name": {
      "first": "Gwen",
      "last": "Case"
    },
    "pseudo": "Gwen2",
    "passWord": "GwenCASE459"
  },
  {
    "idU": 156,
    "name": {
      "first": "Wynn",
      "last": "Woodward"
    },
    "pseudo": "Wynn2",
    "passWord": "WynnWOODWARD848"
  },
  {
    "idU": 157,
    "name": {
      "first": "Hall",
      "last": "Good"
    },
    "pseudo": "Hall8",
    "passWord": "HallGOOD251"
  },
  {
    "idU": 158,
    "name": {
      "first": "Powers",
      "last": "Zimmerman"
    },
    "pseudo": "Powers6",
    "passWord": "PowersZIMMERMAN240"
  },
  {
    "idU": 159,
    "name": {
      "first": "Elise",
      "last": "Mitchell"
    },
    "pseudo": "Elise5",
    "passWord": "EliseMITCHELL656"
  },
  {
    "idU": 160,
    "name": {
      "first": "Hart",
      "last": "Lewis"
    },
    "pseudo": "Hart8",
    "passWord": "HartLEWIS883"
  },
  {
    "idU": 161,
    "name": {
      "first": "Lane",
      "last": "Ashley"
    },
    "pseudo": "Lane5",
    "passWord": "LaneASHLEY611"
  },
  {
    "idU": 162,
    "name": {
      "first": "Rush",
      "last": "Cabrera"
    },
    "pseudo": "Rush4",
    "passWord": "RushCABRERA68"
  },
  {
    "idU": 163,
    "name": {
      "first": "Felecia",
      "last": "Benson"
    },
    "pseudo": "Felecia9",
    "passWord": "FeleciaBENSON666"
  },
  {
    "idU": 164,
    "name": {
      "first": "Valentine",
      "last": "Pugh"
    },
    "pseudo": "Valentine4",
    "passWord": "ValentinePUGH721"
  },
  {
    "idU": 165,
    "name": {
      "first": "Ruthie",
      "last": "Collins"
    },
    "pseudo": "Ruthie7",
    "passWord": "RuthieCOLLINS124"
  },
  {
    "idU": 166,
    "name": {
      "first": "Olga",
      "last": "Nicholson"
    },
    "pseudo": "Olga3",
    "passWord": "OlgaNICHOLSON658"
  },
  {
    "idU": 167,
    "name": {
      "first": "Marla",
      "last": "Hale"
    },
    "pseudo": "Marla10",
    "passWord": "MarlaHALE709"
  },
  {
    "idU": 168,
    "name": {
      "first": "Summer",
      "last": "Burnett"
    },
    "pseudo": "Summer5",
    "passWord": "SummerBURNETT582"
  },
  {
    "idU": 169,
    "name": {
      "first": "Rogers",
      "last": "Jacobson"
    },
    "pseudo": "Rogers1",
    "passWord": "RogersJACOBSON131"
  },
  {
    "idU": 170,
    "name": {
      "first": "Parker",
      "last": "Livingston"
    },
    "pseudo": "Parker3",
    "passWord": "ParkerLIVINGSTON646"
  },
  {
    "idU": 171,
    "name": {
      "first": "Mindy",
      "last": "Workman"
    },
    "pseudo": "Mindy6",
    "passWord": "MindyWORKMAN721"
  },
  {
    "idU": 172,
    "name": {
      "first": "Tate",
      "last": "Tanner"
    },
    "pseudo": "Tate2",
    "passWord": "TateTANNER652"
  },
  {
    "idU": 173,
    "name": {
      "first": "Kaye",
      "last": "Booker"
    },
    "pseudo": "Kaye7",
    "passWord": "KayeBOOKER231"
  },
  {
    "idU": 174,
    "name": {
      "first": "Shannon",
      "last": "Wood"
    },
    "pseudo": "Shannon4",
    "passWord": "ShannonWOOD293"
  },
  {
    "idU": 175,
    "name": {
      "first": "Ruby",
      "last": "Schmidt"
    },
    "pseudo": "Ruby6",
    "passWord": "RubySCHMIDT320"
  },
  {
    "idU": 176,
    "name": {
      "first": "Sandy",
      "last": "Simpson"
    },
    "pseudo": "Sandy7",
    "passWord": "SandySIMPSON716"
  },
  {
    "idU": 177,
    "name": {
      "first": "Josie",
      "last": "Howe"
    },
    "pseudo": "Josie2",
    "passWord": "JosieHOWE613"
  },
  {
    "idU": 178,
    "name": {
      "first": "Guerrero",
      "last": "Hines"
    },
    "pseudo": "Guerrero9",
    "passWord": "GuerreroHINES652"
  },
  {
    "idU": 179,
    "name": {
      "first": "Delgado",
      "last": "Parsons"
    },
    "pseudo": "Delgado5",
    "passWord": "DelgadoPARSONS664"
  },
  {
    "idU": 180,
    "name": {
      "first": "Reid",
      "last": "Ballard"
    },
    "pseudo": "Reid3",
    "passWord": "ReidBALLARD828"
  },
  {
    "idU": 181,
    "name": {
      "first": "Naomi",
      "last": "Young"
    },
    "pseudo": "Naomi6",
    "passWord": "NaomiYOUNG254"
  },
  {
    "idU": 182,
    "name": {
      "first": "Adriana",
      "last": "Harvey"
    },
    "pseudo": "Adriana3",
    "passWord": "AdrianaHARVEY896"
  },
  {
    "idU": 183,
    "name": {
      "first": "Stevens",
      "last": "Vance"
    },
    "pseudo": "Stevens9",
    "passWord": "StevensVANCE109"
  },
  {
    "idU": 184,
    "name": {
      "first": "Neva",
      "last": "Hughes"
    },
    "pseudo": "Neva5",
    "passWord": "NevaHUGHES897"
  },
  {
    "idU": 185,
    "name": {
      "first": "Colette",
      "last": "Mcpherson"
    },
    "pseudo": "Colette8",
    "passWord": "ColetteMCPHERSON617"
  },
  {
    "idU": 186,
    "name": {
      "first": "Clara",
      "last": "Johns"
    },
    "pseudo": "Clara6",
    "passWord": "ClaraJOHNS76"
  },
  {
    "idU": 187,
    "name": {
      "first": "Mattie",
      "last": "Leonard"
    },
    "pseudo": "Mattie10",
    "passWord": "MattieLEONARD74"
  },
  {
    "idU": 188,
    "name": {
      "first": "Valeria",
      "last": "Wheeler"
    },
    "pseudo": "Valeria8",
    "passWord": "ValeriaWHEELER502"
  },
  {
    "idU": 189,
    "name": {
      "first": "Cindy",
      "last": "Osborne"
    },
    "pseudo": "Cindy4",
    "passWord": "CindyOSBORNE531"
  },
  {
    "idU": 190,
    "name": {
      "first": "Beulah",
      "last": "Vang"
    },
    "pseudo": "Beulah9",
    "passWord": "BeulahVANG630"
  },
  {
    "idU": 191,
    "name": {
      "first": "David",
      "last": "Mercer"
    },
    "pseudo": "David9",
    "passWord": "DavidMERCER645"
  },
  {
    "idU": 192,
    "name": {
      "first": "Robles",
      "last": "Hebert"
    },
    "pseudo": "Robles6",
    "passWord": "RoblesHEBERT821"
  },
  {
    "idU": 193,
    "name": {
      "first": "Rivas",
      "last": "Nunez"
    },
    "pseudo": "Rivas10",
    "passWord": "RivasNUNEZ761"
  },
  {
    "idU": 194,
    "name": {
      "first": "Maldonado",
      "last": "Morrison"
    },
    "pseudo": "Maldonado9",
    "passWord": "MaldonadoMORRISON727"
  },
  {
    "idU": 195,
    "name": {
      "first": "Freida",
      "last": "Marshall"
    },
    "pseudo": "Freida9",
    "passWord": "FreidaMARSHALL128"
  },
  {
    "idU": 196,
    "name": {
      "first": "Marjorie",
      "last": "Hays"
    },
    "pseudo": "Marjorie2",
    "passWord": "MarjorieHAYS466"
  },
  {
    "idU": 197,
    "name": {
      "first": "Francis",
      "last": "Guerra"
    },
    "pseudo": "Francis3",
    "passWord": "FrancisGUERRA738"
  },
  {
    "idU": 198,
    "name": {
      "first": "Katherine",
      "last": "Lyons"
    },
    "pseudo": "Katherine4",
    "passWord": "KatherineLYONS508"
  },
  {
    "idU": 199,
    "name": {
      "first": "Ora",
      "last": "Jimenez"
    },
    "pseudo": "Ora8",
    "passWord": "OraJIMENEZ587"
  },
  {
    "idU": 200,
    "name": {
      "first": "Wilkins",
      "last": "Acosta"
    },
    "pseudo": "Wilkins6",
    "passWord": "WilkinsACOSTA175"
  },
  {
    "idU": 201,
    "name": {
      "first": "Delaney",
      "last": "Hartman"
    },
    "pseudo": "Delaney10",
    "passWord": "DelaneyHARTMAN510"
  },
  {
    "idU": 202,
    "name": {
      "first": "Aimee",
      "last": "Forbes"
    },
    "pseudo": "Aimee2",
    "passWord": "AimeeFORBES204"
  },
  {
    "idU": 203,
    "name": {
      "first": "Hollie",
      "last": "Maldonado"
    },
    "pseudo": "Hollie7",
    "passWord": "HollieMALDONADO886"
  },
  {
    "idU": 204,
    "name": {
      "first": "Evans",
      "last": "Langley"
    },
    "pseudo": "Evans2",
    "passWord": "EvansLANGLEY479"
  },
  {
    "idU": 205,
    "name": {
      "first": "Benson",
      "last": "Sullivan"
    },
    "pseudo": "Benson3",
    "passWord": "BensonSULLIVAN790"
  },
  {
    "idU": 206,
    "name": {
      "first": "Gardner",
      "last": "Randall"
    },
    "pseudo": "Gardner6",
    "passWord": "GardnerRANDALL475"
  },
  {
    "idU": 207,
    "name": {
      "first": "Lloyd",
      "last": "Parrish"
    },
    "pseudo": "Lloyd5",
    "passWord": "LloydPARRISH252"
  },
  {
    "idU": 208,
    "name": {
      "first": "Susie",
      "last": "Hull"
    },
    "pseudo": "Susie6",
    "passWord": "SusieHULL788"
  },
  {
    "idU": 209,
    "name": {
      "first": "Gates",
      "last": "Stafford"
    },
    "pseudo": "Gates8",
    "passWord": "GatesSTAFFORD66"
  },
  {
    "idU": 210,
    "name": {
      "first": "Skinner",
      "last": "Potter"
    },
    "pseudo": "Skinner7",
    "passWord": "SkinnerPOTTER603"
  },
  {
    "idU": 211,
    "name": {
      "first": "Earline",
      "last": "Elliott"
    },
    "pseudo": "Earline5",
    "passWord": "EarlineELLIOTT580"
  },
  {
    "idU": 212,
    "name": {
      "first": "Kennedy",
      "last": "Carson"
    },
    "pseudo": "Kennedy7",
    "passWord": "KennedyCARSON496"
  },
  {
    "idU": 213,
    "name": {
      "first": "Lucas",
      "last": "Wise"
    },
    "pseudo": "Lucas9",
    "passWord": "LucasWISE577"
  },
  {
    "idU": 214,
    "name": {
      "first": "Solis",
      "last": "Decker"
    },
    "pseudo": "Solis6",
    "passWord": "SolisDECKER809"
  },
  {
    "idU": 215,
    "name": {
      "first": "Cornelia",
      "last": "Emerson"
    },
    "pseudo": "Cornelia3",
    "passWord": "CorneliaEMERSON613"
  },
  {
    "idU": 216,
    "name": {
      "first": "Annette",
      "last": "Blackwell"
    },
    "pseudo": "Annette10",
    "passWord": "AnnetteBLACKWELL383"
  },
  {
    "idU": 217,
    "name": {
      "first": "Lacey",
      "last": "Gill"
    },
    "pseudo": "Lacey3",
    "passWord": "LaceyGILL429"
  },
  {
    "idU": 218,
    "name": {
      "first": "Donna",
      "last": "Fernandez"
    },
    "pseudo": "Donna5",
    "passWord": "DonnaFERNANDEZ853"
  },
  {
    "idU": 219,
    "name": {
      "first": "Massey",
      "last": "Frank"
    },
    "pseudo": "Massey10",
    "passWord": "MasseyFRANK455"
  },
  {
    "idU": 220,
    "name": {
      "first": "Hodges",
      "last": "Bell"
    },
    "pseudo": "Hodges4",
    "passWord": "HodgesBELL783"
  },
  {
    "idU": 221,
    "name": {
      "first": "Myrtle",
      "last": "Mckee"
    },
    "pseudo": "Myrtle2",
    "passWord": "MyrtleMCKEE827"
  },
  {
    "idU": 222,
    "name": {
      "first": "Martin",
      "last": "Garza"
    },
    "pseudo": "Martin3",
    "passWord": "MartinGARZA874"
  },
  {
    "idU": 223,
    "name": {
      "first": "Heather",
      "last": "Cotton"
    },
    "pseudo": "Heather7",
    "passWord": "HeatherCOTTON202"
  },
  {
    "idU": 224,
    "name": {
      "first": "Alexander",
      "last": "Nolan"
    },
    "pseudo": "Alexander3",
    "passWord": "AlexanderNOLAN785"
  },
  {
    "idU": 225,
    "name": {
      "first": "Caroline",
      "last": "Moran"
    },
    "pseudo": "Caroline1",
    "passWord": "CarolineMORAN84"
  },
  {
    "idU": 226,
    "name": {
      "first": "Keri",
      "last": "Raymond"
    },
    "pseudo": "Keri6",
    "passWord": "KeriRAYMOND170"
  },
  {
    "idU": 227,
    "name": {
      "first": "Carney",
      "last": "Sharp"
    },
    "pseudo": "Carney10",
    "passWord": "CarneySHARP57"
  },
  {
    "idU": 228,
    "name": {
      "first": "Melinda",
      "last": "Bennett"
    },
    "pseudo": "Melinda4",
    "passWord": "MelindaBENNETT37"
  },
  {
    "idU": 229,
    "name": {
      "first": "Dora",
      "last": "Potts"
    },
    "pseudo": "Dora3",
    "passWord": "DoraPOTTS615"
  },
  {
    "idU": 230,
    "name": {
      "first": "Raymond",
      "last": "Rogers"
    },
    "pseudo": "Raymond3",
    "passWord": "RaymondROGERS272"
  },
  {
    "idU": 231,
    "name": {
      "first": "Lora",
      "last": "Mckenzie"
    },
    "pseudo": "Lora9",
    "passWord": "LoraMCKENZIE854"
  },
  {
    "idU": 232,
    "name": {
      "first": "Concetta",
      "last": "Mullen"
    },
    "pseudo": "Concetta2",
    "passWord": "ConcettaMULLEN443"
  },
  {
    "idU": 233,
    "name": {
      "first": "Patsy",
      "last": "Salas"
    },
    "pseudo": "Patsy4",
    "passWord": "PatsySALAS385"
  },
  {
    "idU": 234,
    "name": {
      "first": "Gwendolyn",
      "last": "Bentley"
    },
    "pseudo": "Gwendolyn6",
    "passWord": "GwendolynBENTLEY442"
  },
  {
    "idU": 235,
    "name": {
      "first": "Alford",
      "last": "Wilkerson"
    },
    "pseudo": "Alford1",
    "passWord": "AlfordWILKERSON520"
  },
  {
    "idU": 236,
    "name": {
      "first": "Emily",
      "last": "Vasquez"
    },
    "pseudo": "Emily3",
    "passWord": "EmilyVASQUEZ463"
  },
  {
    "idU": 237,
    "name": {
      "first": "Sharpe",
      "last": "Hardy"
    },
    "pseudo": "Sharpe10",
    "passWord": "SharpeHARDY682"
  },
  {
    "idU": 238,
    "name": {
      "first": "Dodson",
      "last": "Hodge"
    },
    "pseudo": "Dodson4",
    "passWord": "DodsonHODGE574"
  },
  {
    "idU": 239,
    "name": {
      "first": "Marilyn",
      "last": "Espinoza"
    },
    "pseudo": "Marilyn8",
    "passWord": "MarilynESPINOZA467"
  },
  {
    "idU": 240,
    "name": {
      "first": "Maricela",
      "last": "Stephenson"
    },
    "pseudo": "Maricela4",
    "passWord": "MaricelaSTEPHENSON429"
  },
  {
    "idU": 241,
    "name": {
      "first": "Newton",
      "last": "Mayo"
    },
    "pseudo": "Newton8",
    "passWord": "NewtonMAYO114"
  },
  {
    "idU": 242,
    "name": {
      "first": "Burt",
      "last": "Moon"
    },
    "pseudo": "Burt6",
    "passWord": "BurtMOON369"
  },
  {
    "idU": 243,
    "name": {
      "first": "Casandra",
      "last": "Stone"
    },
    "pseudo": "Casandra8",
    "passWord": "CasandraSTONE651"
  },
  {
    "idU": 244,
    "name": {
      "first": "Hayes",
      "last": "Patel"
    },
    "pseudo": "Hayes8",
    "passWord": "HayesPATEL584"
  },
  {
    "idU": 245,
    "name": {
      "first": "Briana",
      "last": "Slater"
    },
    "pseudo": "Briana9",
    "passWord": "BrianaSLATER374"
  },
  {
    "idU": 246,
    "name": {
      "first": "Leon",
      "last": "Mcdaniel"
    },
    "pseudo": "Leon10",
    "passWord": "LeonMCDANIEL586"
  },
  {
    "idU": 247,
    "name": {
      "first": "Lillian",
      "last": "Blair"
    },
    "pseudo": "Lillian1",
    "passWord": "LillianBLAIR723"
  },
  {
    "idU": 248,
    "name": {
      "first": "Nettie",
      "last": "Cleveland"
    },
    "pseudo": "Nettie1",
    "passWord": "NettieCLEVELAND31"
  },
  {
    "idU": 249,
    "name": {
      "first": "Amie",
      "last": "Phillips"
    },
    "pseudo": "Amie8",
    "passWord": "AmiePHILLIPS87"
  },
  {
    "idU": 250,
    "name": {
      "first": "Waters",
      "last": "House"
    },
    "pseudo": "Waters4",
    "passWord": "WatersHOUSE325"
  },
  {
    "idU": 251,
    "name": {
      "first": "Wolf",
      "last": "Bowers"
    },
    "pseudo": "Wolf1",
    "passWord": "WolfBOWERS53"
  },
  {
    "idU": 252,
    "name": {
      "first": "Katie",
      "last": "Carr"
    },
    "pseudo": "Katie9",
    "passWord": "KatieCARR635"
  },
  {
    "idU": 253,
    "name": {
      "first": "Key",
      "last": "Palmer"
    },
    "pseudo": "Key2",
    "passWord": "KeyPALMER419"
  },
  {
    "idU": 254,
    "name": {
      "first": "Erna",
      "last": "Fry"
    },
    "pseudo": "Erna10",
    "passWord": "ErnaFRY301"
  },
  {
    "idU": 255,
    "name": {
      "first": "Garza",
      "last": "Clay"
    },
    "pseudo": "Garza8",
    "passWord": "GarzaCLAY369"
  },
  {
    "idU": 256,
    "name": {
      "first": "Baxter",
      "last": "Flynn"
    },
    "pseudo": "Baxter6",
    "passWord": "BaxterFLYNN215"
  },
  {
    "idU": 257,
    "name": {
      "first": "Aisha",
      "last": "Smith"
    },
    "pseudo": "Aisha10",
    "passWord": "AishaSMITH648"
  },
  {
    "idU": 258,
    "name": {
      "first": "Brianna",
      "last": "Haley"
    },
    "pseudo": "Brianna8",
    "passWord": "BriannaHALEY102"
  },
  {
    "idU": 259,
    "name": {
      "first": "Bass",
      "last": "Ball"
    },
    "pseudo": "Bass8",
    "passWord": "BassBALL286"
  },
  {
    "idU": 260,
    "name": {
      "first": "Marquez",
      "last": "Bridges"
    },
    "pseudo": "Marquez6",
    "passWord": "MarquezBRIDGES800"
  },
  {
    "idU": 261,
    "name": {
      "first": "Suzette",
      "last": "Swanson"
    },
    "pseudo": "Suzette10",
    "passWord": "SuzetteSWANSON150"
  },
  {
    "idU": 262,
    "name": {
      "first": "Cathryn",
      "last": "Yates"
    },
    "pseudo": "Cathryn6",
    "passWord": "CathrynYATES387"
  },
  {
    "idU": 263,
    "name": {
      "first": "Courtney",
      "last": "Craig"
    },
    "pseudo": "Courtney9",
    "passWord": "CourtneyCRAIG422"
  },
  {
    "idU": 264,
    "name": {
      "first": "Tania",
      "last": "Moody"
    },
    "pseudo": "Tania9",
    "passWord": "TaniaMOODY194"
  },
  {
    "idU": 265,
    "name": {
      "first": "Thompson",
      "last": "Kaufman"
    },
    "pseudo": "Thompson1",
    "passWord": "ThompsonKAUFMAN536"
  },
  {
    "idU": 266,
    "name": {
      "first": "Douglas",
      "last": "Cummings"
    },
    "pseudo": "Douglas2",
    "passWord": "DouglasCUMMINGS82"
  },
  {
    "idU": 267,
    "name": {
      "first": "Jenkins",
      "last": "Nieves"
    },
    "pseudo": "Jenkins1",
    "passWord": "JenkinsNIEVES15"
  },
  {
    "idU": 268,
    "name": {
      "first": "Carroll",
      "last": "Pollard"
    },
    "pseudo": "Carroll7",
    "passWord": "CarrollPOLLARD287"
  },
  {
    "idU": 269,
    "name": {
      "first": "Hood",
      "last": "Powell"
    },
    "pseudo": "Hood5",
    "passWord": "HoodPOWELL897"
  },
  {
    "idU": 270,
    "name": {
      "first": "Alma",
      "last": "Wiggins"
    },
    "pseudo": "Alma7",
    "passWord": "AlmaWIGGINS161"
  },
  {
    "idU": 271,
    "name": {
      "first": "Huffman",
      "last": "Cooley"
    },
    "pseudo": "Huffman10",
    "passWord": "HuffmanCOOLEY517"
  },
  {
    "idU": 272,
    "name": {
      "first": "Janell",
      "last": "Walton"
    },
    "pseudo": "Janell9",
    "passWord": "JanellWALTON76"
  },
  {
    "idU": 273,
    "name": {
      "first": "Hooper",
      "last": "Cash"
    },
    "pseudo": "Hooper9",
    "passWord": "HooperCASH860"
  },
  {
    "idU": 274,
    "name": {
      "first": "Hudson",
      "last": "Sutton"
    },
    "pseudo": "Hudson6",
    "passWord": "HudsonSUTTON394"
  },
  {
    "idU": 275,
    "name": {
      "first": "Valarie",
      "last": "Le"
    },
    "pseudo": "Valarie10",
    "passWord": "ValarieLE267"
  },
  {
    "idU": 276,
    "name": {
      "first": "Fleming",
      "last": "Mcconnell"
    },
    "pseudo": "Fleming10",
    "passWord": "FlemingMCCONNELL870"
  },
  {
    "idU": 277,
    "name": {
      "first": "Ilene",
      "last": "Garrett"
    },
    "pseudo": "Ilene5",
    "passWord": "IleneGARRETT622"
  },
  {
    "idU": 278,
    "name": {
      "first": "Tiffany",
      "last": "Garcia"
    },
    "pseudo": "Tiffany8",
    "passWord": "TiffanyGARCIA456"
  },
  {
    "idU": 279,
    "name": {
      "first": "Dee",
      "last": "Barnes"
    },
    "pseudo": "Dee10",
    "passWord": "DeeBARNES31"
  },
  {
    "idU": 280,
    "name": {
      "first": "Conrad",
      "last": "Roy"
    },
    "pseudo": "Conrad3",
    "passWord": "ConradROY642"
  },
  {
    "idU": 281,
    "name": {
      "first": "Lelia",
      "last": "Mason"
    },
    "pseudo": "Lelia1",
    "passWord": "LeliaMASON896"
  },
  {
    "idU": 282,
    "name": {
      "first": "Noelle",
      "last": "Roach"
    },
    "pseudo": "Noelle1",
    "passWord": "NoelleROACH88"
  },
  {
    "idU": 283,
    "name": {
      "first": "Mccall",
      "last": "Gallagher"
    },
    "pseudo": "Mccall10",
    "passWord": "MccallGALLAGHER717"
  },
  {
    "idU": 284,
    "name": {
      "first": "Manuela",
      "last": "Puckett"
    },
    "pseudo": "Manuela1",
    "passWord": "ManuelaPUCKETT610"
  },
  {
    "idU": 285,
    "name": {
      "first": "Pate",
      "last": "Ford"
    },
    "pseudo": "Pate8",
    "passWord": "PateFORD807"
  },
  {
    "idU": 286,
    "name": {
      "first": "Queen",
      "last": "Burns"
    },
    "pseudo": "Queen10",
    "passWord": "QueenBURNS398"
  },
  {
    "idU": 287,
    "name": {
      "first": "Helen",
      "last": "Marsh"
    },
    "pseudo": "Helen6",
    "passWord": "HelenMARSH154"
  },
  {
    "idU": 288,
    "name": {
      "first": "Jane",
      "last": "Boone"
    },
    "pseudo": "Jane4",
    "passWord": "JaneBOONE812"
  },
  {
    "idU": 289,
    "name": {
      "first": "Luisa",
      "last": "Burke"
    },
    "pseudo": "Luisa10",
    "passWord": "LuisaBURKE742"
  },
  {
    "idU": 290,
    "name": {
      "first": "Daniels",
      "last": "Tran"
    },
    "pseudo": "Daniels4",
    "passWord": "DanielsTRAN301"
  },
  {
    "idU": 291,
    "name": {
      "first": "Merle",
      "last": "Landry"
    },
    "pseudo": "Merle3",
    "passWord": "MerleLANDRY668"
  },
  {
    "idU": 292,
    "name": {
      "first": "Hanson",
      "last": "Ewing"
    },
    "pseudo": "Hanson3",
    "passWord": "HansonEWING383"
  },
  {
    "idU": 293,
    "name": {
      "first": "Addie",
      "last": "Mays"
    },
    "pseudo": "Addie6",
    "passWord": "AddieMAYS746"
  },
  {
    "idU": 294,
    "name": {
      "first": "Francisca",
      "last": "Finley"
    },
    "pseudo": "Francisca4",
    "passWord": "FranciscaFINLEY56"
  },
  {
    "idU": 295,
    "name": {
      "first": "Munoz",
      "last": "Clarke"
    },
    "pseudo": "Munoz2",
    "passWord": "MunozCLARKE848"
  },
  {
    "idU": 296,
    "name": {
      "first": "Combs",
      "last": "Rodriquez"
    },
    "pseudo": "Combs8",
    "passWord": "CombsRODRIQUEZ814"
  },
  {
    "idU": 297,
    "name": {
      "first": "Faye",
      "last": "Britt"
    },
    "pseudo": "Faye5",
    "passWord": "FayeBRITT847"
  },
  {
    "idU": 298,
    "name": {
      "first": "Shaw",
      "last": "Santos"
    },
    "pseudo": "Shaw8",
    "passWord": "ShawSANTOS116"
  },
  {
    "idU": 299,
    "name": {
      "first": "Denise",
      "last": "Boyle"
    },
    "pseudo": "Denise10",
    "passWord": "DeniseBOYLE214"
  },
  {
    "idU": 300,
    "name": {
      "first": "Gladys",
      "last": "Sandoval"
    },
    "pseudo": "Gladys4",
    "passWord": "GladysSANDOVAL291"
  },
  {
    "idU": 301,
    "name": {
      "first": "Kate",
      "last": "Wagner"
    },
    "pseudo": "Kate10",
    "passWord": "KateWAGNER283"
  },
  {
    "idU": 302,
    "name": {
      "first": "Wood",
      "last": "Koch"
    },
    "pseudo": "Wood9",
    "passWord": "WoodKOCH141"
  },
  {
    "idU": 303,
    "name": {
      "first": "Samantha",
      "last": "Sargent"
    },
    "pseudo": "Samantha7",
    "passWord": "SamanthaSARGENT731"
  },
  {
    "idU": 304,
    "name": {
      "first": "Crosby",
      "last": "Stuart"
    },
    "pseudo": "Crosby6",
    "passWord": "CrosbySTUART588"
  },
  {
    "idU": 305,
    "name": {
      "first": "Sherri",
      "last": "Park"
    },
    "pseudo": "Sherri9",
    "passWord": "SherriPARK606"
  },
  {
    "idU": 306,
    "name": {
      "first": "Trevino",
      "last": "Tyler"
    },
    "pseudo": "Trevino1",
    "passWord": "TrevinoTYLER49"
  },
  {
    "idU": 307,
    "name": {
      "first": "Jessica",
      "last": "Duffy"
    },
    "pseudo": "Jessica4",
    "passWord": "JessicaDUFFY881"
  },
  {
    "idU": 308,
    "name": {
      "first": "Franco",
      "last": "Hurst"
    },
    "pseudo": "Franco3",
    "passWord": "FrancoHURST312"
  },
  {
    "idU": 309,
    "name": {
      "first": "Lawrence",
      "last": "Merritt"
    },
    "pseudo": "Lawrence3",
    "passWord": "LawrenceMERRITT88"
  },
  {
    "idU": 310,
    "name": {
      "first": "Celina",
      "last": "Mooney"
    },
    "pseudo": "Celina2",
    "passWord": "CelinaMOONEY371"
  },
  {
    "idU": 311,
    "name": {
      "first": "Kramer",
      "last": "Leach"
    },
    "pseudo": "Kramer2",
    "passWord": "KramerLEACH748"
  },
  {
    "idU": 312,
    "name": {
      "first": "Rosa",
      "last": "Trevino"
    },
    "pseudo": "Rosa1",
    "passWord": "RosaTREVINO524"
  },
  {
    "idU": 313,
    "name": {
      "first": "Beth",
      "last": "Lee"
    },
    "pseudo": "Beth7",
    "passWord": "BethLEE874"
  },
  {
    "idU": 314,
    "name": {
      "first": "Marks",
      "last": "Dawson"
    },
    "pseudo": "Marks10",
    "passWord": "MarksDAWSON476"
  },
  {
    "idU": 315,
    "name": {
      "first": "Daniel",
      "last": "Hickman"
    },
    "pseudo": "Daniel4",
    "passWord": "DanielHICKMAN631"
  },
  {
    "idU": 316,
    "name": {
      "first": "Abbott",
      "last": "Farrell"
    },
    "pseudo": "Abbott9",
    "passWord": "AbbottFARRELL320"
  },
  {
    "idU": 317,
    "name": {
      "first": "Sondra",
      "last": "Freeman"
    },
    "pseudo": "Sondra2",
    "passWord": "SondraFREEMAN427"
  },
  {
    "idU": 318,
    "name": {
      "first": "Holt",
      "last": "Hess"
    },
    "pseudo": "Holt8",
    "passWord": "HoltHESS20"
  },
  {
    "idU": 319,
    "name": {
      "first": "Giles",
      "last": "Browning"
    },
    "pseudo": "Giles7",
    "passWord": "GilesBROWNING173"
  },
  {
    "idU": 320,
    "name": {
      "first": "Ester",
      "last": "Blake"
    },
    "pseudo": "Ester4",
    "passWord": "EsterBLAKE608"
  },
  {
    "idU": 321,
    "name": {
      "first": "Long",
      "last": "Warner"
    },
    "pseudo": "Long7",
    "passWord": "LongWARNER409"
  },
  {
    "idU": 322,
    "name": {
      "first": "Perkins",
      "last": "Cain"
    },
    "pseudo": "Perkins2",
    "passWord": "PerkinsCAIN714"
  },
  {
    "idU": 323,
    "name": {
      "first": "Huber",
      "last": "Martinez"
    },
    "pseudo": "Huber8",
    "passWord": "HuberMARTINEZ170"
  },
  {
    "idU": 324,
    "name": {
      "first": "Donovan",
      "last": "Hall"
    },
    "pseudo": "Donovan8",
    "passWord": "DonovanHALL597"
  },
  {
    "idU": 325,
    "name": {
      "first": "Shannon",
      "last": "Wall"
    },
    "pseudo": "Shannon9",
    "passWord": "ShannonWALL123"
  },
  {
    "idU": 326,
    "name": {
      "first": "Gretchen",
      "last": "Pennington"
    },
    "pseudo": "Gretchen5",
    "passWord": "GretchenPENNINGTON625"
  },
  {
    "idU": 327,
    "name": {
      "first": "Meghan",
      "last": "Knapp"
    },
    "pseudo": "Meghan7",
    "passWord": "MeghanKNAPP176"
  },
  {
    "idU": 328,
    "name": {
      "first": "Davidson",
      "last": "Blanchard"
    },
    "pseudo": "Davidson4",
    "passWord": "DavidsonBLANCHARD498"
  },
  {
    "idU": 329,
    "name": {
      "first": "Macias",
      "last": "Marks"
    },
    "pseudo": "Macias1",
    "passWord": "MaciasMARKS573"
  },
  {
    "idU": 330,
    "name": {
      "first": "Kathy",
      "last": "Church"
    },
    "pseudo": "Kathy5",
    "passWord": "KathyCHURCH351"
  },
  {
    "idU": 331,
    "name": {
      "first": "Williams",
      "last": "Hansen"
    },
    "pseudo": "Williams2",
    "passWord": "WilliamsHANSEN693"
  },
  {
    "idU": 332,
    "name": {
      "first": "Roberts",
      "last": "Moore"
    },
    "pseudo": "Roberts6",
    "passWord": "RobertsMOORE761"
  },
  {
    "idU": 333,
    "name": {
      "first": "Dale",
      "last": "Morales"
    },
    "pseudo": "Dale7",
    "passWord": "DaleMORALES499"
  },
  {
    "idU": 334,
    "name": {
      "first": "Rhoda",
      "last": "Alford"
    },
    "pseudo": "Rhoda10",
    "passWord": "RhodaALFORD125"
  },
  {
    "idU": 335,
    "name": {
      "first": "Martha",
      "last": "Guerrero"
    },
    "pseudo": "Martha2",
    "passWord": "MarthaGUERRERO69"
  },
  {
    "idU": 336,
    "name": {
      "first": "Gina",
      "last": "Valencia"
    },
    "pseudo": "Gina2",
    "passWord": "GinaVALENCIA771"
  },
  {
    "idU": 337,
    "name": {
      "first": "Celeste",
      "last": "Hawkins"
    },
    "pseudo": "Celeste1",
    "passWord": "CelesteHAWKINS190"
  },
  {
    "idU": 338,
    "name": {
      "first": "Ines",
      "last": "White"
    },
    "pseudo": "Ines4",
    "passWord": "InesWHITE327"
  },
  {
    "idU": 339,
    "name": {
      "first": "Penny",
      "last": "Lawson"
    },
    "pseudo": "Penny5",
    "passWord": "PennyLAWSON252"
  },
  {
    "idU": 340,
    "name": {
      "first": "Wagner",
      "last": "Orr"
    },
    "pseudo": "Wagner6",
    "passWord": "WagnerORR510"
  },
  {
    "idU": 341,
    "name": {
      "first": "Jackie",
      "last": "Foster"
    },
    "pseudo": "Jackie9",
    "passWord": "JackieFOSTER365"
  },
  {
    "idU": 342,
    "name": {
      "first": "Daugherty",
      "last": "Joyce"
    },
    "pseudo": "Daugherty9",
    "passWord": "DaughertyJOYCE192"
  },
  {
    "idU": 343,
    "name": {
      "first": "Ray",
      "last": "Ellis"
    },
    "pseudo": "Ray9",
    "passWord": "RayELLIS829"
  },
  {
    "idU": 344,
    "name": {
      "first": "Maxwell",
      "last": "Haney"
    },
    "pseudo": "Maxwell1",
    "passWord": "MaxwellHANEY410"
  },
  {
    "idU": 345,
    "name": {
      "first": "Sullivan",
      "last": "Anthony"
    },
    "pseudo": "Sullivan1",
    "passWord": "SullivanANTHONY173"
  },
  {
    "idU": 346,
    "name": {
      "first": "Jeanine",
      "last": "Paul"
    },
    "pseudo": "Jeanine1",
    "passWord": "JeaninePAUL734"
  },
  {
    "idU": 347,
    "name": {
      "first": "Irene",
      "last": "Oconnor"
    },
    "pseudo": "Irene10",
    "passWord": "IreneOCONNOR386"
  },
  {
    "idU": 348,
    "name": {
      "first": "Vargas",
      "last": "Ortiz"
    },
    "pseudo": "Vargas7",
    "passWord": "VargasORTIZ10"
  },
  {
    "idU": 349,
    "name": {
      "first": "Annabelle",
      "last": "Barry"
    },
    "pseudo": "Annabelle3",
    "passWord": "AnnabelleBARRY533"
  },
  {
    "idU": 350,
    "name": {
      "first": "Kidd",
      "last": "Cervantes"
    },
    "pseudo": "Kidd4",
    "passWord": "KiddCERVANTES621"
  },
  {
    "idU": 351,
    "name": {
      "first": "Pierce",
      "last": "Harrison"
    },
    "pseudo": "Pierce3",
    "passWord": "PierceHARRISON565"
  },
  {
    "idU": 352,
    "name": {
      "first": "Paulette",
      "last": "Baxter"
    },
    "pseudo": "Paulette4",
    "passWord": "PauletteBAXTER594"
  },
  {
    "idU": 353,
    "name": {
      "first": "Ferrell",
      "last": "Duran"
    },
    "pseudo": "Ferrell9",
    "passWord": "FerrellDURAN787"
  },
  {
    "idU": 354,
    "name": {
      "first": "Janice",
      "last": "Washington"
    },
    "pseudo": "Janice4",
    "passWord": "JaniceWASHINGTON470"
  },
  {
    "idU": 355,
    "name": {
      "first": "Calhoun",
      "last": "Mckinney"
    },
    "pseudo": "Calhoun4",
    "passWord": "CalhounMCKINNEY70"
  },
  {
    "idU": 356,
    "name": {
      "first": "Marisa",
      "last": "Weaver"
    },
    "pseudo": "Marisa1",
    "passWord": "MarisaWEAVER785"
  },
  {
    "idU": 357,
    "name": {
      "first": "Wooten",
      "last": "Figueroa"
    },
    "pseudo": "Wooten1",
    "passWord": "WootenFIGUEROA617"
  },
  {
    "idU": 358,
    "name": {
      "first": "Dillard",
      "last": "Rojas"
    },
    "pseudo": "Dillard4",
    "passWord": "DillardROJAS421"
  },
  {
    "idU": 359,
    "name": {
      "first": "Mendez",
      "last": "Holder"
    },
    "pseudo": "Mendez3",
    "passWord": "MendezHOLDER724"
  },
  {
    "idU": 360,
    "name": {
      "first": "Mccarthy",
      "last": "Thomas"
    },
    "pseudo": "Mccarthy7",
    "passWord": "MccarthyTHOMAS445"
  },
  {
    "idU": 361,
    "name": {
      "first": "Pansy",
      "last": "Kinney"
    },
    "pseudo": "Pansy7",
    "passWord": "PansyKINNEY669"
  },
  {
    "idU": 362,
    "name": {
      "first": "Santana",
      "last": "Holcomb"
    },
    "pseudo": "Santana3",
    "passWord": "SantanaHOLCOMB770"
  },
  {
    "idU": 363,
    "name": {
      "first": "Victoria",
      "last": "Dale"
    },
    "pseudo": "Victoria1",
    "passWord": "VictoriaDALE152"
  },
  {
    "idU": 364,
    "name": {
      "first": "Rasmussen",
      "last": "Goodwin"
    },
    "pseudo": "Rasmussen5",
    "passWord": "RasmussenGOODWIN17"
  },
  {
    "idU": 365,
    "name": {
      "first": "Mercado",
      "last": "Hester"
    },
    "pseudo": "Mercado9",
    "passWord": "MercadoHESTER375"
  },
  {
    "idU": 366,
    "name": {
      "first": "Angeline",
      "last": "Mccullough"
    },
    "pseudo": "Angeline8",
    "passWord": "AngelineMCCULLOUGH792"
  },
  {
    "idU": 367,
    "name": {
      "first": "Allison",
      "last": "Herrera"
    },
    "pseudo": "Allison7",
    "passWord": "AllisonHERRERA895"
  },
  {
    "idU": 368,
    "name": {
      "first": "Imogene",
      "last": "Lester"
    },
    "pseudo": "Imogene5",
    "passWord": "ImogeneLESTER895"
  },
  {
    "idU": 369,
    "name": {
      "first": "Matthews",
      "last": "Wynn"
    },
    "pseudo": "Matthews6",
    "passWord": "MatthewsWYNN635"
  },
  {
    "idU": 370,
    "name": {
      "first": "Terry",
      "last": "Webster"
    },
    "pseudo": "Terry10",
    "passWord": "TerryWEBSTER787"
  },
  {
    "idU": 371,
    "name": {
      "first": "Strong",
      "last": "Shelton"
    },
    "pseudo": "Strong7",
    "passWord": "StrongSHELTON871"
  },
  {
    "idU": 372,
    "name": {
      "first": "Hannah",
      "last": "Stewart"
    },
    "pseudo": "Hannah3",
    "passWord": "HannahSTEWART776"
  },
  {
    "idU": 373,
    "name": {
      "first": "Gamble",
      "last": "Lancaster"
    },
    "pseudo": "Gamble2",
    "passWord": "GambleLANCASTER700"
  },
  {
    "idU": 374,
    "name": {
      "first": "Christie",
      "last": "Fischer"
    },
    "pseudo": "Christie5",
    "passWord": "ChristieFISCHER830"
  },
  {
    "idU": 375,
    "name": {
      "first": "Brennan",
      "last": "Bauer"
    },
    "pseudo": "Brennan10",
    "passWord": "BrennanBAUER699"
  },
  {
    "idU": 376,
    "name": {
      "first": "Stephens",
      "last": "Oneil"
    },
    "pseudo": "Stephens9",
    "passWord": "StephensONEIL275"
  },
  {
    "idU": 377,
    "name": {
      "first": "Lena",
      "last": "Bray"
    },
    "pseudo": "Lena2",
    "passWord": "LenaBRAY773"
  },
  {
    "idU": 378,
    "name": {
      "first": "Concepcion",
      "last": "Reilly"
    },
    "pseudo": "Concepcion3",
    "passWord": "ConcepcionREILLY504"
  },
  {
    "idU": 379,
    "name": {
      "first": "Oneal",
      "last": "Gray"
    },
    "pseudo": "Oneal8",
    "passWord": "OnealGRAY689"
  },
  {
    "idU": 380,
    "name": {
      "first": "Meadows",
      "last": "Petersen"
    },
    "pseudo": "Meadows6",
    "passWord": "MeadowsPETERSEN192"
  },
  {
    "idU": 381,
    "name": {
      "first": "Julia",
      "last": "Garrison"
    },
    "pseudo": "Julia9",
    "passWord": "JuliaGARRISON799"
  },
  {
    "idU": 382,
    "name": {
      "first": "Cortez",
      "last": "Chan"
    },
    "pseudo": "Cortez2",
    "passWord": "CortezCHAN450"
  },
  {
    "idU": 383,
    "name": {
      "first": "Georgette",
      "last": "Bates"
    },
    "pseudo": "Georgette3",
    "passWord": "GeorgetteBATES701"
  },
  {
    "idU": 384,
    "name": {
      "first": "Hilda",
      "last": "Sharpe"
    },
    "pseudo": "Hilda9",
    "passWord": "HildaSHARPE417"
  },
  {
    "idU": 385,
    "name": {
      "first": "Murray",
      "last": "Beach"
    },
    "pseudo": "Murray1",
    "passWord": "MurrayBEACH523"
  },
  {
    "idU": 386,
    "name": {
      "first": "Mallory",
      "last": "Reynolds"
    },
    "pseudo": "Mallory6",
    "passWord": "MalloryREYNOLDS345"
  },
  {
    "idU": 387,
    "name": {
      "first": "Chasity",
      "last": "Solomon"
    },
    "pseudo": "Chasity5",
    "passWord": "ChasitySOLOMON101"
  },
  {
    "idU": 388,
    "name": {
      "first": "Stella",
      "last": "Guzman"
    },
    "pseudo": "Stella8",
    "passWord": "StellaGUZMAN190"
  },
  {
    "idU": 389,
    "name": {
      "first": "Clark",
      "last": "Phelps"
    },
    "pseudo": "Clark8",
    "passWord": "ClarkPHELPS336"
  },
  {
    "idU": 390,
    "name": {
      "first": "Wyatt",
      "last": "Navarro"
    },
    "pseudo": "Wyatt7",
    "passWord": "WyattNAVARRO570"
  },
  {
    "idU": 391,
    "name": {
      "first": "Hillary",
      "last": "Copeland"
    },
    "pseudo": "Hillary4",
    "passWord": "HillaryCOPELAND304"
  },
  {
    "idU": 392,
    "name": {
      "first": "Marianne",
      "last": "Griffin"
    },
    "pseudo": "Marianne6",
    "passWord": "MarianneGRIFFIN316"
  },
  {
    "idU": 393,
    "name": {
      "first": "Jerri",
      "last": "Bishop"
    },
    "pseudo": "Jerri7",
    "passWord": "JerriBISHOP834"
  },
  {
    "idU": 394,
    "name": {
      "first": "Benita",
      "last": "Aguirre"
    },
    "pseudo": "Benita2",
    "passWord": "BenitaAGUIRRE286"
  },
  {
    "idU": 395,
    "name": {
      "first": "Paul",
      "last": "Sherman"
    },
    "pseudo": "Paul10",
    "passWord": "PaulSHERMAN763"
  },
  {
    "idU": 396,
    "name": {
      "first": "Mayer",
      "last": "Castro"
    },
    "pseudo": "Mayer10",
    "passWord": "MayerCASTRO521"
  },
  {
    "idU": 397,
    "name": {
      "first": "Cara",
      "last": "Riley"
    },
    "pseudo": "Cara5",
    "passWord": "CaraRILEY123"
  },
  {
    "idU": 398,
    "name": {
      "first": "Hoover",
      "last": "Alston"
    },
    "pseudo": "Hoover1",
    "passWord": "HooverALSTON75"
  },
  {
    "idU": 399,
    "name": {
      "first": "Joan",
      "last": "Terrell"
    },
    "pseudo": "Joan2",
    "passWord": "JoanTERRELL627"
  },
  {
    "idU": 400,
    "name": {
      "first": "Dotson",
      "last": "Gardner"
    },
    "pseudo": "Dotson3",
    "passWord": "DotsonGARDNER751"
  },
  {
    "idU": 401,
    "name": {
      "first": "Lynch",
      "last": "Becker"
    },
    "pseudo": "Lynch8",
    "passWord": "LynchBECKER600"
  },
  {
    "idU": 402,
    "name": {
      "first": "Natalia",
      "last": "Hinton"
    },
    "pseudo": "Natalia4",
    "passWord": "NataliaHINTON845"
  },
  {
    "idU": 403,
    "name": {
      "first": "Sara",
      "last": "Knight"
    },
    "pseudo": "Sara2",
    "passWord": "SaraKNIGHT163"
  },
  {
    "idU": 404,
    "name": {
      "first": "Tyler",
      "last": "Mathis"
    },
    "pseudo": "Tyler3",
    "passWord": "TylerMATHIS759"
  },
  {
    "idU": 405,
    "name": {
      "first": "Robbins",
      "last": "Stanley"
    },
    "pseudo": "Robbins8",
    "passWord": "RobbinsSTANLEY234"
  },
  {
    "idU": 406,
    "name": {
      "first": "Allyson",
      "last": "Daniel"
    },
    "pseudo": "Allyson2",
    "passWord": "AllysonDANIEL174"
  },
  {
    "idU": 407,
    "name": {
      "first": "Yang",
      "last": "Schwartz"
    },
    "pseudo": "Yang5",
    "passWord": "YangSCHWARTZ490"
  },
  {
    "idU": 408,
    "name": {
      "first": "Judy",
      "last": "Nguyen"
    },
    "pseudo": "Judy5",
    "passWord": "JudyNGUYEN733"
  },
  {
    "idU": 409,
    "name": {
      "first": "Mari",
      "last": "Wallace"
    },
    "pseudo": "Mari6",
    "passWord": "MariWALLACE506"
  },
  {
    "idU": 410,
    "name": {
      "first": "Morton",
      "last": "Green"
    },
    "pseudo": "Morton10",
    "passWord": "MortonGREEN770"
  },
  {
    "idU": 411,
    "name": {
      "first": "Imelda",
      "last": "Brock"
    },
    "pseudo": "Imelda6",
    "passWord": "ImeldaBROCK539"
  },
  {
    "idU": 412,
    "name": {
      "first": "Shelby",
      "last": "Clark"
    },
    "pseudo": "Shelby6",
    "passWord": "ShelbyCLARK659"
  },
  {
    "idU": 413,
    "name": {
      "first": "Kathleen",
      "last": "Goodman"
    },
    "pseudo": "Kathleen8",
    "passWord": "KathleenGOODMAN622"
  },
  {
    "idU": 414,
    "name": {
      "first": "Dudley",
      "last": "Savage"
    },
    "pseudo": "Dudley10",
    "passWord": "DudleySAVAGE55"
  },
  {
    "idU": 415,
    "name": {
      "first": "Juana",
      "last": "Manning"
    },
    "pseudo": "Juana1",
    "passWord": "JuanaMANNING587"
  },
  {
    "idU": 416,
    "name": {
      "first": "Hendricks",
      "last": "Whitley"
    },
    "pseudo": "Hendricks10",
    "passWord": "HendricksWHITLEY77"
  },
  {
    "idU": 417,
    "name": {
      "first": "Caldwell",
      "last": "Evans"
    },
    "pseudo": "Caldwell1",
    "passWord": "CaldwellEVANS641"
  },
  {
    "idU": 418,
    "name": {
      "first": "Deena",
      "last": "Dean"
    },
    "pseudo": "Deena10",
    "passWord": "DeenaDEAN771"
  },
  {
    "idU": 419,
    "name": {
      "first": "Rachelle",
      "last": "Patterson"
    },
    "pseudo": "Rachelle2",
    "passWord": "RachellePATTERSON575"
  },
  {
    "idU": 420,
    "name": {
      "first": "Campos",
      "last": "Vega"
    },
    "pseudo": "Campos6",
    "passWord": "CamposVEGA84"
  },
  {
    "idU": 421,
    "name": {
      "first": "Acosta",
      "last": "Lane"
    },
    "pseudo": "Acosta2",
    "passWord": "AcostaLANE730"
  },
  {
    "idU": 422,
    "name": {
      "first": "Barbara",
      "last": "Callahan"
    },
    "pseudo": "Barbara4",
    "passWord": "BarbaraCALLAHAN215"
  },
  {
    "idU": 423,
    "name": {
      "first": "Jacquelyn",
      "last": "Reid"
    },
    "pseudo": "Jacquelyn1",
    "passWord": "JacquelynREID9"
  },
  {
    "idU": 424,
    "name": {
      "first": "Margaret",
      "last": "Sanford"
    },
    "pseudo": "Margaret6",
    "passWord": "MargaretSANFORD463"
  },
  {
    "idU": 425,
    "name": {
      "first": "Savage",
      "last": "Jarvis"
    },
    "pseudo": "Savage10",
    "passWord": "SavageJARVIS457"
  },
  {
    "idU": 426,
    "name": {
      "first": "Michael",
      "last": "Wells"
    },
    "pseudo": "Michael4",
    "passWord": "MichaelWELLS24"
  },
  {
    "idU": 427,
    "name": {
      "first": "Sophia",
      "last": "Short"
    },
    "pseudo": "Sophia10",
    "passWord": "SophiaSHORT348"
  },
  {
    "idU": 428,
    "name": {
      "first": "Lessie",
      "last": "Coffey"
    },
    "pseudo": "Lessie9",
    "passWord": "LessieCOFFEY373"
  },
  {
    "idU": 429,
    "name": {
      "first": "Ursula",
      "last": "Fowler"
    },
    "pseudo": "Ursula6",
    "passWord": "UrsulaFOWLER689"
  },
  {
    "idU": 430,
    "name": {
      "first": "Hatfield",
      "last": "Huffman"
    },
    "pseudo": "Hatfield1",
    "passWord": "HatfieldHUFFMAN424"
  },
  {
    "idU": 431,
    "name": {
      "first": "June",
      "last": "Joyner"
    },
    "pseudo": "June10",
    "passWord": "JuneJOYNER426"
  },
  {
    "idU": 432,
    "name": {
      "first": "Lenore",
      "last": "Gilmore"
    },
    "pseudo": "Lenore1",
    "passWord": "LenoreGILMORE518"
  },
  {
    "idU": 433,
    "name": {
      "first": "Blankenship",
      "last": "Mcmahon"
    },
    "pseudo": "Blankenship9",
    "passWord": "BlankenshipMCMAHON254"
  },
  {
    "idU": 434,
    "name": {
      "first": "Kimberly",
      "last": "Austin"
    },
    "pseudo": "Kimberly2",
    "passWord": "KimberlyAUSTIN870"
  },
  {
    "idU": 435,
    "name": {
      "first": "Calderon",
      "last": "Dodson"
    },
    "pseudo": "Calderon6",
    "passWord": "CalderonDODSON452"
  },
  {
    "idU": 436,
    "name": {
      "first": "Cathy",
      "last": "Villarreal"
    },
    "pseudo": "Cathy8",
    "passWord": "CathyVILLARREAL809"
  },
  {
    "idU": 437,
    "name": {
      "first": "Chelsea",
      "last": "Contreras"
    },
    "pseudo": "Chelsea6",
    "passWord": "ChelseaCONTRERAS714"
  },
  {
    "idU": 438,
    "name": {
      "first": "Christina",
      "last": "Pruitt"
    },
    "pseudo": "Christina1",
    "passWord": "ChristinaPRUITT724"
  },
  {
    "idU": 439,
    "name": {
      "first": "Geneva",
      "last": "Bean"
    },
    "pseudo": "Geneva9",
    "passWord": "GenevaBEAN179"
  },
  {
    "idU": 440,
    "name": {
      "first": "Rocha",
      "last": "Riggs"
    },
    "pseudo": "Rocha4",
    "passWord": "RochaRIGGS306"
  },
  {
    "idU": 441,
    "name": {
      "first": "Frazier",
      "last": "Olson"
    },
    "pseudo": "Frazier3",
    "passWord": "FrazierOLSON570"
  },
  {
    "idU": 442,
    "name": {
      "first": "Tracie",
      "last": "Chen"
    },
    "pseudo": "Tracie3",
    "passWord": "TracieCHEN456"
  },
  {
    "idU": 443,
    "name": {
      "first": "Kline",
      "last": "Hobbs"
    },
    "pseudo": "Kline6",
    "passWord": "KlineHOBBS290"
  },
  {
    "idU": 444,
    "name": {
      "first": "Vance",
      "last": "Weeks"
    },
    "pseudo": "Vance5",
    "passWord": "VanceWEEKS484"
  },
  {
    "idU": 445,
    "name": {
      "first": "Fowler",
      "last": "Ramsey"
    },
    "pseudo": "Fowler9",
    "passWord": "FowlerRAMSEY729"
  },
  {
    "idU": 446,
    "name": {
      "first": "Mathis",
      "last": "Curtis"
    },
    "pseudo": "Mathis3",
    "passWord": "MathisCURTIS435"
  },
  {
    "idU": 447,
    "name": {
      "first": "Cruz",
      "last": "Cooper"
    },
    "pseudo": "Cruz2",
    "passWord": "CruzCOOPER578"
  },
  {
    "idU": 448,
    "name": {
      "first": "Gabriela",
      "last": "Strong"
    },
    "pseudo": "Gabriela6",
    "passWord": "GabrielaSTRONG661"
  },
  {
    "idU": 449,
    "name": {
      "first": "Mabel",
      "last": "Petty"
    },
    "pseudo": "Mabel1",
    "passWord": "MabelPETTY297"
  },
  {
    "idU": 450,
    "name": {
      "first": "Black",
      "last": "Dillard"
    },
    "pseudo": "Black1",
    "passWord": "BlackDILLARD355"
  },
  {
    "idU": 451,
    "name": {
      "first": "Talley",
      "last": "Ellison"
    },
    "pseudo": "Talley1",
    "passWord": "TalleyELLISON321"
  },
  {
    "idU": 452,
    "name": {
      "first": "Roseann",
      "last": "Kennedy"
    },
    "pseudo": "Roseann4",
    "passWord": "RoseannKENNEDY358"
  },
  {
    "idU": 453,
    "name": {
      "first": "Duncan",
      "last": "French"
    },
    "pseudo": "Duncan2",
    "passWord": "DuncanFRENCH581"
  },
  {
    "idU": 454,
    "name": {
      "first": "Wolfe",
      "last": "Rodriguez"
    },
    "pseudo": "Wolfe1",
    "passWord": "WolfeRODRIGUEZ39"
  },
  {
    "idU": 455,
    "name": {
      "first": "Juliet",
      "last": "Allen"
    },
    "pseudo": "Juliet7",
    "passWord": "JulietALLEN808"
  },
  {
    "idU": 456,
    "name": {
      "first": "Josefa",
      "last": "Everett"
    },
    "pseudo": "Josefa6",
    "passWord": "JosefaEVERETT406"
  },
  {
    "idU": 457,
    "name": {
      "first": "Consuelo",
      "last": "Jensen"
    },
    "pseudo": "Consuelo4",
    "passWord": "ConsueloJENSEN636"
  },
  {
    "idU": 458,
    "name": {
      "first": "Juliana",
      "last": "Brown"
    },
    "pseudo": "Juliana3",
    "passWord": "JulianaBROWN525"
  },
  {
    "idU": 459,
    "name": {
      "first": "Durham",
      "last": "Houston"
    },
    "pseudo": "Durham5",
    "passWord": "DurhamHOUSTON91"
  },
  {
    "idU": 460,
    "name": {
      "first": "Ana",
      "last": "Hunt"
    },
    "pseudo": "Ana5",
    "passWord": "AnaHUNT900"
  },
  {
    "idU": 461,
    "name": {
      "first": "Workman",
      "last": "Grant"
    },
    "pseudo": "Workman10",
    "passWord": "WorkmanGRANT398"
  },
  {
    "idU": 462,
    "name": {
      "first": "Aguilar",
      "last": "Shaw"
    },
    "pseudo": "Aguilar1",
    "passWord": "AguilarSHAW163"
  },
  {
    "idU": 463,
    "name": {
      "first": "Nellie",
      "last": "Henson"
    },
    "pseudo": "Nellie4",
    "passWord": "NellieHENSON283"
  },
  {
    "idU": 464,
    "name": {
      "first": "Kelli",
      "last": "Scott"
    },
    "pseudo": "Kelli4",
    "passWord": "KelliSCOTT540"
  },
  {
    "idU": 465,
    "name": {
      "first": "Roxie",
      "last": "Burris"
    },
    "pseudo": "Roxie4",
    "passWord": "RoxieBURRIS121"
  },
  {
    "idU": 466,
    "name": {
      "first": "Valdez",
      "last": "Day"
    },
    "pseudo": "Valdez9",
    "passWord": "ValdezDAY423"
  },
  {
    "idU": 467,
    "name": {
      "first": "Karyn",
      "last": "Butler"
    },
    "pseudo": "Karyn3",
    "passWord": "KarynBUTLER467"
  },
  {
    "idU": 468,
    "name": {
      "first": "Randi",
      "last": "Hancock"
    },
    "pseudo": "Randi3",
    "passWord": "RandiHANCOCK642"
  },
  {
    "idU": 469,
    "name": {
      "first": "Scott",
      "last": "Harrington"
    },
    "pseudo": "Scott4",
    "passWord": "ScottHARRINGTON879"
  },
  {
    "idU": 470,
    "name": {
      "first": "Coleen",
      "last": "Rios"
    },
    "pseudo": "Coleen6",
    "passWord": "ColeenRIOS593"
  },
  {
    "idU": 471,
    "name": {
      "first": "Keith",
      "last": "Mann"
    },
    "pseudo": "Keith10",
    "passWord": "KeithMANN577"
  },
  {
    "idU": 472,
    "name": {
      "first": "Bernadette",
      "last": "Donovan"
    },
    "pseudo": "Bernadette7",
    "passWord": "BernadetteDONOVAN841"
  },
  {
    "idU": 473,
    "name": {
      "first": "Goldie",
      "last": "Guy"
    },
    "pseudo": "Goldie1",
    "passWord": "GoldieGUY318"
  },
  {
    "idU": 474,
    "name": {
      "first": "Angelita",
      "last": "Clements"
    },
    "pseudo": "Angelita7",
    "passWord": "AngelitaCLEMENTS267"
  },
  {
    "idU": 475,
    "name": {
      "first": "Pacheco",
      "last": "Bartlett"
    },
    "pseudo": "Pacheco5",
    "passWord": "PachecoBARTLETT861"
  },
  {
    "idU": 476,
    "name": {
      "first": "Bettie",
      "last": "Cross"
    },
    "pseudo": "Bettie5",
    "passWord": "BettieCROSS327"
  },
  {
    "idU": 477,
    "name": {
      "first": "Shelley",
      "last": "Sawyer"
    },
    "pseudo": "Shelley10",
    "passWord": "ShelleySAWYER693"
  },
  {
    "idU": 478,
    "name": {
      "first": "Dollie",
      "last": "Levy"
    },
    "pseudo": "Dollie6",
    "passWord": "DollieLEVY459"
  },
  {
    "idU": 479,
    "name": {
      "first": "Gomez",
      "last": "Lopez"
    },
    "pseudo": "Gomez4",
    "passWord": "GomezLOPEZ306"
  },
  {
    "idU": 480,
    "name": {
      "first": "Carpenter",
      "last": "Snider"
    },
    "pseudo": "Carpenter9",
    "passWord": "CarpenterSNIDER191"
  },
  {
    "idU": 481,
    "name": {
      "first": "Morrow",
      "last": "Hamilton"
    },
    "pseudo": "Morrow6",
    "passWord": "MorrowHAMILTON565"
  },
  {
    "idU": 482,
    "name": {
      "first": "Monroe",
      "last": "Humphrey"
    },
    "pseudo": "Monroe2",
    "passWord": "MonroeHUMPHREY484"
  },
  {
    "idU": 483,
    "name": {
      "first": "Hammond",
      "last": "Irwin"
    },
    "pseudo": "Hammond5",
    "passWord": "HammondIRWIN526"
  },
  {
    "idU": 484,
    "name": {
      "first": "Maryellen",
      "last": "Poole"
    },
    "pseudo": "Maryellen10",
    "passWord": "MaryellenPOOLE129"
  },
  {
    "idU": 485,
    "name": {
      "first": "Evangelina",
      "last": "Maddox"
    },
    "pseudo": "Evangelina3",
    "passWord": "EvangelinaMADDOX634"
  },
  {
    "idU": 486,
    "name": {
      "first": "Pearlie",
      "last": "Deleon"
    },
    "pseudo": "Pearlie6",
    "passWord": "PearlieDELEON571"
  },
  {
    "idU": 487,
    "name": {
      "first": "Rodgers",
      "last": "Hudson"
    },
    "pseudo": "Rodgers10",
    "passWord": "RodgersHUDSON741"
  },
  {
    "idU": 488,
    "name": {
      "first": "Tina",
      "last": "Robertson"
    },
    "pseudo": "Tina2",
    "passWord": "TinaROBERTSON242"
  },
  {
    "idU": 489,
    "name": {
      "first": "Salinas",
      "last": "Mcfarland"
    },
    "pseudo": "Salinas4",
    "passWord": "SalinasMCFARLAND136"
  },
  {
    "idU": 490,
    "name": {
      "first": "Glenda",
      "last": "Gregory"
    },
    "pseudo": "Glenda6",
    "passWord": "GlendaGREGORY423"
  },
  {
    "idU": 491,
    "name": {
      "first": "Veronica",
      "last": "Townsend"
    },
    "pseudo": "Veronica7",
    "passWord": "VeronicaTOWNSEND807"
  },
  {
    "idU": 492,
    "name": {
      "first": "Barron",
      "last": "Miller"
    },
    "pseudo": "Barron3",
    "passWord": "BarronMILLER677"
  },
  {
    "idU": 493,
    "name": {
      "first": "Renee",
      "last": "Foley"
    },
    "pseudo": "Renee1",
    "passWord": "ReneeFOLEY196"
  },
  {
    "idU": 494,
    "name": {
      "first": "Lottie",
      "last": "Armstrong"
    },
    "pseudo": "Lottie5",
    "passWord": "LottieARMSTRONG164"
  },
  {
    "idU": 495,
    "name": {
      "first": "Jeanne",
      "last": "Trujillo"
    },
    "pseudo": "Jeanne10",
    "passWord": "JeanneTRUJILLO87"
  },
  {
    "idU": 496,
    "name": {
      "first": "Cline",
      "last": "Hatfield"
    },
    "pseudo": "Cline7",
    "passWord": "ClineHATFIELD165"
  },
  {
    "idU": 497,
    "name": {
      "first": "Carey",
      "last": "Keith"
    },
    "pseudo": "Carey1",
    "passWord": "CareyKEITH840"
  },
  {
    "idU": 498,
    "name": {
      "first": "Battle",
      "last": "Mcdowell"
    },
    "pseudo": "Battle4",
    "passWord": "BattleMCDOWELL338"
  },
  {
    "idU": 499,
    "name": {
      "first": "Wallace",
      "last": "Gibson"
    },
    "pseudo": "Wallace1",
    "passWord": "WallaceGIBSON738"
  }
]